{"cameraMode":{"drawMode":0,"name":"Shaded","section":"Shading Mode"},"sceneLighting":true,"audioPlay":false,"sceneViewState":{"showFog":true,"showMaterialUpdate":false,"showSkybox":true,"showFlares":true,"showImageEffects":true,"showParticleSystems":true},"in2DMode":false,"pivot":{"x":0.6438699960708618,"y":1.375780463218689,"z":-0.05048029124736786},"rotation":{"x":-0.21707072854042054,"y":0.6455389857292175,"z":-0.19885319471359254,"w":-0.7047221660614014},"size":0.5486354231834412,"orthographic":false}